helppy/KB.p
helppy/__init__.py
helppy/helppy.py
helppy-0.1.5.dist-info/LICENCE
helppy-0.1.5.dist-info/METADATA
helppy-0.1.5.dist-info/WHEEL
helppy-0.1.5.dist-info/top_level.txt
helppy-0.1.5.dist-info/RECORD
